jageocoder_dbtool/__init__.py
jageocoder_dbtool/__main__.py
jageocoder_dbtool/convertor.py
jageocoder_dbtool/customtypes.py
jageocoder_dbtool/data/aliases.json
jageocoder_dbtool/data_manager.py
jageocoder_dbtool/metadata.py
jageocoder_dbtool/spatial.py
jageocoder_dbtool-0.2.4.dist-info/LICENSE
jageocoder_dbtool-0.2.4.dist-info/METADATA
jageocoder_dbtool-0.2.4.dist-info/WHEEL
jageocoder_dbtool-0.2.4.dist-info/entry_points.txt
jageocoder_dbtool-0.2.4.dist-info/RECORD
