Metadata-Version: 2.3
Name: jageocoder-dbtool
Version: 0.2.4
Summary: Address database management tool for Jageocoder.
License: BSD-2-Clause
Author: GeoNLP Platform
Maintainer: Takeshi Sagara
Maintainer-email: sagara@info-proto.com
Requires-Python: >=3.10,<3.13
Classifier: Development Status :: 4 - Beta
Classifier: License :: OSI Approved :: BSD License
Classifier: Operating System :: MacOS :: MacOS X
Classifier: Operating System :: Microsoft :: Windows :: Windows 11
Classifier: Operating System :: POSIX :: Linux
Classifier: Programming Language :: Python :: 3
Classifier: Programming Language :: Python :: 3.10
Classifier: Programming Language :: Python :: 3.11
Classifier: Programming Language :: Python :: 3.12
Requires-Dist: docopt-ng
Requires-Dist: jageocoder (>=2.1.9)
Requires-Dist: pyproj (>=3.7.1,<4.0.0)
Requires-Dist: shapely (>=2.1.0,<3.0.0)
Requires-Dist: tqdm (>=4.67.1,<5.0.0)
Project-URL: Bug Tracker, https://github.com/geonlp-platform/jageocoder-dbtool/issues
Project-URL: repository, https://github.com/geonlp-platform/jageocoder-dbtool
